AUTHORS.rst
CONTRIBUTING.rst
HISTORY.rst
LICENSE
MANIFEST.in
README.rst
setup.cfg
setup.py
docs/Makefile
docs/authors.rst
docs/conf.py
docs/contributing.rst
docs/history.rst
docs/index.rst
docs/installation.rst
docs/make.bat
docs/readme.rst
docs/usage.rst
randgen_generator_bsp/__init__.py
randgen_generator_bsp/cli.py
randgen_generator_bsp/randgen_generator_bsp.py
randgen_generator_bsp.egg-info/PKG-INFO
randgen_generator_bsp.egg-info/SOURCES.txt
randgen_generator_bsp.egg-info/dependency_links.txt
randgen_generator_bsp.egg-info/entry_points.txt
randgen_generator_bsp.egg-info/not-zip-safe
randgen_generator_bsp.egg-info/requires.txt
randgen_generator_bsp.egg-info/top_level.txt
tests/__init__.py
tests/test_randgen_generator_bsp.py