Metadata-Version: 1.1
Name: randgen-generator-bsp
Version: 0.1.1
Summary: BSP random map generator for randgen.io.
Home-page: https://github.com/lxndrdagreat/randgen_generator_bsp
Author: Dan Alexander
Author-email: lxndrdagreat@gmail.com
License: MIT license
Keywords: randgen_generator_bsp
Platform: UNKNOWN
Classifier: Development Status :: 2 - Pre-Alpha
Classifier: Intended Audience :: Developers
Classifier: License :: OSI Approved :: MIT License
Classifier: Natural Language :: English
Classifier: Programming Language :: Python :: 2
Classifier: Programming Language :: Python :: 2.6
Classifier: Programming Language :: Python :: 2.7
Classifier: Programming Language :: Python :: 3
Classifier: Programming Language :: Python :: 3.3
Classifier: Programming Language :: Python :: 3.4
Classifier: Programming Language :: Python :: 3.5
